[
    {
        "id": 1,
        "title": "Tecno-mobile-skytech (Full-Stack)",
        "images": "https://i.ibb.co/QmPm7QP/Techno-Skytech-Mobile.png",
        "points1": "✔️ This project uses JS, React, MongoDB, Node.js, Bootstrap, And FirebaseThis is a complete UI based website. ",
        "points2": " ✔️ Here you can easily order one or more products and see all the orders if you want. And if you want you can delete orders. If the user wants, he can give a review which will be added to the home page.",
        "points3": "✔️ Admins can add new products if they want and can create more than one admin if they want. And can confirm orders.",
        "technology": "#Html #Css3 #Bootstrap #JS #React #React Router #Firebase",
        "liveLink": "https://tecno-mobile-skytech.web.app/",
        "clientGit": "https://github.com/MDALSABBIR/Tecno-Mobile-Skytech-client-Side",
        "serverGit": "https://github.com/MDALSABBIR/Tecno-Mobile-Skytech-ServerSide",
        "linkedIn": "https://www.linkedin.com/in/md-alsabbir-1066/"
    },
    {
        "id": 2,
        "title": "Unitravel-torism-agency (Full-Stack)",
        "images": "https://i.ibb.co/s1sGK7t/Uni-Travel-Agency.png",
        "points1": "✔️ This is a complete UI-based website. This project uses JS, React, MongoDB, Node.js, Bootstrap, And Firebase.",
        "points2": " ✔️ Different login systems have been provided on this website. If you want you can login in different ways.",
        "points3": " ✔️ You can book one or more services if you want. You can view your bookings if you want. And if you want you can delete your bookings.",
        "technology": "#Html #Css3 #Bootstrap #JS #React #React Router #Firebase",
        "liveLink": "https://unitravel-torism-agency.web.app/",
        "clientGit": "https://github.com/MDALSABBIR/Uni-Travel-Agency-Client-side",
        "serverGit": "https://github.com/MDALSABBIR/unitravel-torism-agency-server-side",
        "linkedIn": "https://www.linkedin.com/in/md-alsabbir-1066/"
    },
    {
        "id": 3,
        "title": "Developing Master (Front-end)",
        "images": "https://i.ibb.co/GPQkfGZ/developer.png",
        "points1": "✔️ This is a different style and design-focused website. This project uses JS, React, Bootstrap, CSS, And Font awesome.",
        "points2": " ✔️ Different sections are styled differently.",
        "points3": " ✔️ Different colors have been given in different places focusing on color combinations.",
        "technology": "#Html #Css3 #Bootstrap #JS #React Router",
        "liveLink": "https://developing-master.netlify.app/",
        "clientGit": "https://github.com/ProgrammingHeroWC4/review-website-MDALSABBIR",
        "linkedIn": "https://www.linkedin.com/in/md-alsabbir-1066/"
    }
]